diffindiff/__init__.py
diffindiff/config.py
diffindiff/didanalysis.py
diffindiff/didanalysis_helper.py
diffindiff/diddata.py
diffindiff/didtools.py
diffindiff/tests/__init__.py
diffindiff/tests/tests_diffindiff.py
diffindiff/tests/data/Corona_Hesse.xlsx
diffindiff/tests/data/counties_DE.csv
diffindiff/tests/data/curfew_DE.csv
diffindiff-2.2.4.dist-info/METADATA
diffindiff-2.2.4.dist-info/WHEEL
diffindiff-2.2.4.dist-info/top_level.txt
diffindiff-2.2.4.dist-info/RECORD
