Metadata-Version: 2.1
Name: diffindiff
Version: 2.2.4
Summary: diffindiff: Python library for convenient Difference-in-Differences Analyses
Author: Thomas Wieland
Author-email: geowieland@googlemail.com
Requires-Dist: numpy
Requires-Dist: pandas
Requires-Dist: statsmodels==0.14.2
Requires-Dist: scipy==1.15.3
Requires-Dist: matplotlib
Requires-Dist: datetime
Requires-Dist: scikit-learn
Requires-Dist: xgboost
Requires-Dist: lightgbm
Requires-Dist: patsy
Requires-Dist: openpyxl
Requires-Dist: huff>=1.6.6
